appdynamics/CHANGELOG.md
appdynamics/CONTROLLER_DEPENDENCY_VERSION
appdynamics/LICENSE
appdynamics/VERSION
appdynamics/__init__.py
appdynamics/aiohttp_lib.py
appdynamics/asgi_lib.py
appdynamics/config.py
appdynamics/lang.py
appdynamics/lib.py
appdynamics/pep425tags.py
appdynamics/priority_dict.py
appdynamics/_vendor/__init__.py
appdynamics/_vendor/six.py
appdynamics/_vendor/structlog/__init__.py
appdynamics/_vendor/structlog/_base.py
appdynamics/_vendor/structlog/_config.py
appdynamics/_vendor/structlog/_frames.py
appdynamics/_vendor/structlog/_generic.py
appdynamics/_vendor/structlog/_loggers.py
appdynamics/_vendor/structlog/_utils.py
appdynamics/_vendor/structlog/dev.py
appdynamics/_vendor/structlog/exceptions.py
appdynamics/_vendor/structlog/processors.py
appdynamics/_vendor/structlog/six.py
appdynamics/_vendor/structlog/stdlib.py
appdynamics/_vendor/structlog/threadlocal.py
appdynamics/_vendor/structlog/twisted.py
appdynamics/agent/__init__.py
appdynamics/agent/api/__init__.py
appdynamics/agent/api/api.py
appdynamics/agent/core/__init__.py
appdynamics/agent/core/agent.py
appdynamics/agent/core/conditions.py
appdynamics/agent/core/context.py
appdynamics/agent/core/correlation.py
appdynamics/agent/core/eum.py
appdynamics/agent/core/expressions.py
appdynamics/agent/core/logs.py
appdynamics/agent/core/method_data_gatherer.py
appdynamics/agent/core/naming.py
appdynamics/agent/core/pb.py
appdynamics/agent/core/registries.py
appdynamics/agent/core/snapshot.py
appdynamics/agent/core/timer.py
appdynamics/agent/core/transport.py
appdynamics/agent/interceptor/__init__.py
appdynamics/agent/interceptor/base.py
appdynamics/agent/interceptor/cache/__init__.py
appdynamics/agent/interceptor/cache/memcache.py
appdynamics/agent/interceptor/cache/redis.py
appdynamics/agent/interceptor/frameworks/__init__.py
appdynamics/agent/interceptor/frameworks/aiohttp_web.py
appdynamics/agent/interceptor/frameworks/asgi.py
appdynamics/agent/interceptor/frameworks/bottle.py
appdynamics-25.8.0.8120.dist-info/METADATA
appdynamics-25.8.0.8120.dist-info/WHEEL
appdynamics-25.8.0.8120.dist-info/entry_points.txt
appdynamics-25.8.0.8120.dist-info/top_level.txt
appdynamics-25.8.0.8120.dist-info/RECORD
